polytopes/__init__.py
polytopes/accelerated_polytopical_costs.py
polytopes/chord_movement.py
polytopes/compute_frontiers.py
polytopes/compute_scores.py
polytopes/data_manipulation.py
polytopes/pattern_factory.py
polytopes/pattern_manip.py
polytopes/polytopical_costs.py
polytopes/segmentation_algorithms.py
polytopes/segmentation_helper.py
polytopes/triad_transformations.py
polytopes/voiceleading_utilities.py
polytopes/model/__init__.py
polytopes/model/chord.py
polytopes/model/constants.py
polytopes/model/errors.py
polytopes/model/note.py
polytopes/model/triad_manipulation.py
MusicOnPolytopes-0.1.0.dist-info/AUTHORS
MusicOnPolytopes-0.1.0.dist-info/LICENSE
MusicOnPolytopes-0.1.0.dist-info/METADATA
MusicOnPolytopes-0.1.0.dist-info/WHEEL
MusicOnPolytopes-0.1.0.dist-info/top_level.txt
MusicOnPolytopes-0.1.0.dist-info/RECORD
