Metadata-Version: 2.1
Name: MusicOnPolytopes
Version: 0.1.0
Summary: Package for polytopic intepretation of music, with application to musical segmentation
Home-page: https://gitlab.inria.fr/amarmore/musiconpolytopes
Author: Marmoret Axel
Author-email: axel.marmoret@irisa.fr
License: BSD
Classifier: License :: OSI Approved :: BSD License
Classifier: Programming Language :: Python
Classifier: Development Status :: 3 - Alpha
Classifier: Intended Audience :: Developers
Classifier: Intended Audience :: Science/Research
Classifier: Topic :: Multimedia :: Sound/Audio :: Analysis
Classifier: Programming Language :: Python :: 3.7
Requires-Python: >=3.7
License-File: LICENSE
License-File: AUTHORS
Requires-Dist: mir-eval
Requires-Dist: numpy (>=1.18.0)
